xjenza_gen/__init__.py
xjenza_gen/article.py
xjenza_gen/insertable.py
xjenza_gen/latex.py
xjenza_gen/main.py
xjenza_gen/outputs/figs/test_fig.png
xjenza_gen/outputs/packages/logo.pdf
xjenza_gen/outputs/packages/xjenza-preamble.tex
xjenza_gen/outputs/packages/xjenza.sty
xjenza_gen/outputs/references.bib
xjenza_gen/prompts.py
xjenza_gen/templates/main.tex
xjenza_gen-0.1.4.dist-info/METADATA
xjenza_gen-0.1.4.dist-info/WHEEL
xjenza_gen-0.1.4.dist-info/entry_points.txt
xjenza_gen-0.1.4.dist-info/RECORD
