Metadata-Version: 2.1
Name: xjenza-gen
Version: 0.1.4
Summary: 
Author: girogio
Author-email: giorgiogrigolo03@gmail.com
Requires-Python: >=3.10,<4.0
Classifier: Programming Language :: Python :: 3
Classifier: Programming Language :: Python :: 3.10
Classifier: Programming Language :: Python :: 3.11
Classifier: Programming Language :: Python :: 3.12
Requires-Dist: latexbuild (>=0.2.2,<0.3.0)
Requires-Dist: pylatexenc (>=2.10,<3.0)
Requires-Dist: requests (>=2.31.0,<3.0.0)
Requires-Dist: rich (>=13.7.0,<14.0.0)
Requires-Dist: typer (>=0.9.0,<0.10.0)
